newsFeedClassifier-CS331/ExceptionNotSeen.py
newsFeedClassifier-CS331/__init__.py
newsFeedClassifier-CS331/classifier.py
newsFeedClassifier-CS331/tokenizer.py
newsFeedClassifier-CS331/trainedData.py
newsFeedClassifier-CS331/trainer.py
newsFeedClassifierBayesianCS331/ExceptionNotSeen.py
newsFeedClassifierBayesianCS331/__init__.py
newsFeedClassifierBayesianCS331/classifier.py
newsFeedClassifierBayesianCS331/tokenizer.py
newsFeedClassifierBayesianCS331/trainedData.py
newsFeedClassifierBayesianCS331/trainer.py
newsFeedClassifierBayesianCS331-2.0.1.dist-info/DESCRIPTION.rst
newsFeedClassifierBayesianCS331-2.0.1.dist-info/METADATA
newsFeedClassifierBayesianCS331-2.0.1.dist-info/RECORD
newsFeedClassifierBayesianCS331-2.0.1.dist-info/WHEEL
newsFeedClassifierBayesianCS331-2.0.1.dist-info/metadata.json
newsFeedClassifierBayesianCS331-2.0.1.dist-info/top_level.txt
newsFeedClassifierCS331/ExceptionNotSeen.py
newsFeedClassifierCS331/__init__.py
newsFeedClassifierCS331/classifier.py
newsFeedClassifierCS331/tokenizer.py
newsFeedClassifierCS331/trainedData.py
newsFeedClassifierCS331/trainer.py
